ecv_python_development/__init__.py
ecv_python_development/py.typed
ecv_python_development/aws_cloud_native/__init__.py
ecv_python_development/aws_cloud_native/events_module/__init__.py
ecv_python_development/aws_cloud_native/events_module/base.py
ecv_python_development/aws_cloud_native/lambda_module/__init__.py
ecv_python_development/aws_cloud_native/lambda_module/exceptions.py
ecv_python_development/aws_cloud_native/lambda_module/handler.py
ecv_python_development/aws_cloud_native/lambda_module/logger.py
ecv_python_development/aws_cloud_native/lambda_module/metrics.py
ecv_python_development/aws_cloud_native/lambda_module/response.py
ecv_python_development/aws_cloud_native/lambda_module/tracer.py
ecv_python_development/aws_cloud_native/lambda_module/validator.py
ecv_python_development/aws_cloud_native/services/__init__.py
ecv_python_development/aws_cloud_native/services/aws_service.py
ecv_python_development/aws_cloud_native/services/cognito_service.py
ecv_python_development/aws_cloud_native/services/dynamodb_service.py
ecv_python_development/aws_cloud_native/services/eventbridge_service.py
ecv_python_development/aws_cloud_native/services/exceptions.py
ecv_python_development/aws_cloud_native/services/kms_service.py
ecv_python_development/aws_cloud_native/services/lambda_service.py
ecv_python_development/aws_cloud_native/services/s3_service.py
ecv_python_development/aws_cloud_native/services/secretsmanager_service.py
ecv_python_development/aws_cloud_native/services/ses_service.py
ecv_python_development/aws_cloud_native/services/sns_service.py
ecv_python_development/aws_cloud_native/services/sqs_service.py
ecv_python_development/aws_cloud_native/services/ssm_service.py
ecv_python_development/database/__init__.py
ecv_python_development/database/base_model.py
ecv_python_development/database/test.py
ecv_python_development/database/_pynamodb/__init__.py
ecv_python_development/database/_pynamodb/base.py
ecv_python_development/helpers/__init__.py
ecv_python_development-0.0.60.dist-info/LICENSE
ecv_python_development-0.0.60.dist-info/METADATA
ecv_python_development-0.0.60.dist-info/WHEEL
ecv_python_development-0.0.60.dist-info/top_level.txt
ecv_python_development-0.0.60.dist-info/RECORD
